<?xml version="1.0" encoding="windows-1251"?>
<!-- edited with XMLSpy v2014 sp1 (x64) (http://www.altova.com) by work (Irkutskzheldorproekt, branch of Roszheldorproekt, JSC) -->
<Words>
	<word first="bookkeeper" second="бухгалтер"/>
	<word first="writer" second="писатель"/>
	<word first="teacher" second="учитель"/>
	<word first="photographer" second="фотограф"/>
	<word first="dancer" second="танцор"/>
	<word first="dentist" second="дантист"/>
	<word first="policeman" second="полицейский"/>
	<word first="lawyer" second="эрист"/>
	<word first="journalist" second="журналист"/>
	<word first="doctor" second="доктор"/>
	<word first="economist" second="экономист"/>
	<word first="driver" second="водитель"/>
	<word first="farmer" second="фермер"/>
	<word first="cook" second="повар"/>
	<word first="hairdresser" second="парикмахер"/>
	<word first="singer" second="певец"/>
	<word first="postman" second="почтальон"/>
	<word first="engineer" second="инженер"/>
	<word first="salesperson" second="продавец"/>
	<word first="fireman" second="пожарный"/>
</Words>
